Workbook

Sheet Anexo A
E2: DIRECCIÓN GENERAL DE IMPUESTOS INTERNOS
E3: DECLARACIÓN JURADA Y/O PAGO DEL IMPUESTO SOBRE LAS TRANSFERENCIAS DE BIENES INDUSTRIALIZADOS Y SERVICIOS (ITBIS)
B5: I. | C5: DATOS GENERALES | Z5: =+IF(#REF!="",1,2) -> #REF!
C6: RNC/CÉDULA | I6: RAZÓN SOCIAL/NOMBRE | Q6: NOMBRE COMERCIAL
D9: CORREO ELECTRÓNICO | M9: TELÉFONO | Q9: PERÍODO (MES/AÑO) | T9: FECHA LÍMITE DE PAGO | W9: TIPO DE DECLARACIÓN
B14: II. | C14: OPERACIONES REPORTADAS EN EL 607, LIBRO DE VENTAS Y FACTURA ELECTRONICA (E-NCF) POR TIPO DE NCF | T14: CANTIDAD | W14: MONTO
B15: 1 | C15: COMPROBANTES VÁLIDO PARA CRÉDITO FISCAL (01 y 31) | V15: +
B16: =+B15+1 -> 2 | C16: COMPROBANTES CONSUMO (02 y 32) | V16: +
B17: =+B16+1 -> 3 | C17: COMPROBANTES NOTA DE DÉBITO (03 y 33) | V17: +
B18: =+B17+1 -> 4 | C18: COMPROBANTES NOTA DE CRÉDITO (04 y 34) | V18: -
B19: =+B18+1 -> 5 | C19: COMPROBANTES REGISTRO ÚNICO DE INGRESOS (12) | V19: +
B20: =+B19+1 -> 6 | C20: COMPROBANTES REGISTRO REGIMENES ESPECIALES (14 y 44) | V20: +
B21: =+B20+1 -> 7 | C21: COMPROBANTES GUBERNAMENTALES (15 y 45) | V21: +
B22: =+B21+1 -> 8 | C22: COMPROBANTES PARA EXPORTACIONES (16 y 46) | V22: +
B23: =+B22+1 -> 9 | C23: OTRAS OPERACIONES (POSITIVAS) | V23: +
B24: =+B23+1 -> 10 | C24: OTRAS OPERACIONES (NEGATIVAS) | V24: -
B25: =+B24+1 -> 11 | C25: TOTAL OPERACIONES (Sumar casillas 1+2+3-4+5+6+7+8+9-10) | V25: = | W25: =W15+W16+W17+W19+W20+W21+W22+W23-W18-W24 -> 0
B27: III. | C27: OPERACIONES REPORTADAS EN EL 607/LIBRO DE VENTAS Y FACTURA ELECTRONICA (E-NCF) POR TIPO DE VENTA (MONTO TOTAL INCLUYENDO IMPUESTOS) | W27: MONTO BRUTO
B28: =+B25+1 -> 12 | C28: EFECTIVO | V28: +
B29: =+B28+1 -> 13 | C29: CHEQUE / TRANSFERENCIA | V29: +
B30: =+B29+1 -> 14 | C30: TARJETA DÉBITO / CRÉDITO | V30: +
B31: =+B30+1 -> 15 | C31: A CRÉDITO | V31: +
B32: =+B31+1 -> 16 | C32: BONOS O CERTIFICADO DE REGALO | V32: +
B33: =+B32+1 -> 17 | C33: PERMUTAS | V33: +
B34: =+B33+1 -> 18 | C34: OTRAS FORMAS DE VENTA | V34: +
B35: =+B34+1 -> 19 | C35: TOTAL OPERACIONES POR TIPO DE VENTA (Sumar casillas 12+13+14+15+16+17+18) | V35: = | W35: =ABS(SUM(W28:X34)) -> 0
B37: IV. | C37: OPERACIONES REPORTADAS EN EL 607/LIBRO DE VENTAS Y FACTURA ELECTRONICA (E-NCF) POR TIPO DE INGRESO | W37: MONTO
B38: =+B35+1 -> 20 | C38: INGRESOS POR OPERACIONES (NO FINANCIEROS) | V38: +
B39: =+B38+1 -> 21 | C39: INGRESOS FINANCIEROS | V39: +
B40: =+B39+1 -> 22 | C40: INGRESOS EXTRAORDINARIOS | V40: +
B41: =+B40+1 -> 23 | C41: INGRESOS POR ARRENDAMIENTOS | V41: +
B42: =+B41+1 -> 24 | C42: INGRESOS POR VENTAS DE ACTIVOS DEPRECIABLES | V42: +
B43: =+B42+1 -> 25 | C43: OTROS INGRESOS | V43: +
B44: =+B43+1 -> 26 | C44: TOTAL POR TIPO DE INGRESO (Sumar casillas 20+21+22+23+24+25) | V44: = | W44: =ABS(SUM(W38:X43)) -> 0
B46: V. | C46: PAGOS COMPUTABLES POR RETENCIONES/PERCEPCIÓN | W46: MONTO
B47: =B44+1 -> 27 | C47: PAGOS COMPUTABLES POR RETENCIONES (Norma No. 08-04) | V47: +
B48: =+B47+1 -> 28 | C48: PAGOS COMPUTABLES POR VENTAS DE PASAJES DE TRANSPORTE AÉREO (Norma No. 02-05) (BSP-IATA) | V48: +
B49: =+B48+1 -> 29 | C49: PAGOS COMPUTABLES POR OTRAS RETENCIONES (Norma No. 02-05) | V49: +
B50: =+B49+1 -> 30 | C50: PAGOS COMPUTABLES POR VENTAS DE PAQUETES DE ALOJAMIENTO Y OCUPACIÓN | V50: +
B51: =+B50+1 -> 31 | C51: CRÉDITO POR RETENCIÓN REALIZADA POR ENTIDADES DEL ESTADO | V51: +
B52: =+B51+1 -> 32 | C52: PAGOS COMPUTABLES POR ITBIS PERCIBIDO | V52: +
B53: =+B52+1 -> 33 | C53: TOTAL PAGOS COMPUTABLES POR RETENCIONES/PERCEPCIÓN (Sumar casillas 27+28+29+30+31+32) | V53: = | W53: =ABS(SUM(W47:X52)) -> 0
B55: VI. | C55: OPERACIONES DE CONSTRUCTORAS | T55: TOTAL FACTURADO | W55: MONTO
B56: =B53+1 -> 34 | C56: DIRECCIÓN TÉCNICA (Art. 4 Norma 07-07) | S56: + | V56: + | W56: =T56*10% -> 0
B57: =+B56+1 -> 35 | C57: CONTRATO DE ADMINISTRACIÓN (Art. 4 Párrafo I, Norma 07-07) | S57: + | V57: +
B58: =+B57+1 -> 36 | C58: ASESORIAS / HONORARIOS | V58: +
B59: =+B58+1 -> 37 | C59: TOTAL OPERACIONES CONSTRUCTORAS (Total Facturado: Sumar casillas 34+35, Monto: Sumar casillas 34+35+36) | S59: = | T59: =ABS(SUM(T56:U57)) -> 0 | V59: = | W59: =ABS(SUM(W56:X58)) -> 0
B60: =B59+1 -> 38 | C60: OPERACIONES NO SUJETAS A ITBIS POR SERVICIOS DE CONSTRUCCIÓN (Restar Casilla 37 Total Facturado - Monto Sujeto a ITBIS) | V60: = | W60: =IF(T59-W59<0,0,T59-W59) -> 0
B62: VII. | C62: OPERACIONES DE COMISIONISTAS | T62: TOTAL FACTURADO | W62: MONTO
B63: =+B60+1 -> 39 | C63: VENTAS DE BIENES POR COMISIÓN | S63: + | V63: +
B64: =+B63+1 -> 40 | C64: VENTAS DE SERVICIOS EN NOMBRE DE TERCEROS | S64: + | V64: +
B65: =B64+1 -> 41 | C65: TOTAL OPERACIONES COMISIONISTAS (Sumar casillas 39+40) | S65: = | T65: =ABS(SUM(T63:U64)) -> 0 | V65: = | W65: =ABS(SUM(W63:X64)) -> 0
B66: =B65+1 -> 42 | C66: OPERACIONES NO SUJETAS A ITBIS POR COMISIONES (Restar Casilla 41 Total Facturado - Monto Sujeto a ITBIS) | V66: = | W66: =IF(T65-W65<0,0,T65-W65) -> 0
B68: VIII. | C68: DATOS INFORMATIVOS | W68: MONTO
B69: =+B66+1 -> 43 | C69: TOTAL NOTAS DE CRÉDITO EMITIDAS CON MÁS DE TREINTA (30) DÍAS DESDE LA FACTURACIÓN (Art. 338 CT) | V69: =
B70: =+B69+1 -> 44 | C70: TOTAL FACTURAS EN COMPROBANTES FISCALES PARA REGIMENES ESPECIALES (Proviene del Formato 606) | V70: =
B72: IX. | C72: ITBIS PAGADO | O72: COMPRAS LOCALES * | P72: SERVICIOS * | T72: IMPORTACIONES | W72: TOTAL
B73: A) | C73: NO DEDUCIBLE (Llevado al Costo/Gasto)
B74: =+B70+1 -> 45 | C74: EN OPERACIONES DE PRODUCTORES DE BIENES O SERVICIOS EXENTOS | W74: =SUM(O74:V74) -> 0
B75: =+B74+1 -> 46 | C75: A INCLUIR EN ACTIVOS (CATEGORÍA I) | W75: =SUM(O75:V75) -> 0
B76: =+B75+1 -> 47 | C76: OTROS ITBIS PAGADOS NO DEDUCIBLES | W76: =SUM(O76:V76) -> 0
B77: =+B76+1 -> 48 | C77: TOTAL ITBIS NO DEDUCIBLE (45+46+47) | O77: =SUM(O74:O76) -> 0 | P77: =SUM(P74:S76) -> 0 | T77: =SUM(T74:V76) -> 0 | W77: =SUM(O77:V77) -> 0
B78: B) | C78: DEDUCIBLE
B79: =+B77+1 -> 49 | C79: EN LA PRODUCCIÓN Y/O VENTA DE BIENES EXPORTADOS | W79: =SUM(O79:V79) -> 0
B80: =+B79+1 -> 50 | C80: EN LA PRODUCCIÓN Y/O VENTA DE BIENES GRAVADOS | W80: =SUM(O80:V80) -> 0
B81: =B80+1 -> 51 | C81: EN LA PRESTACIÓN DE SERVICIOS GRAVADOS | W81: =SUM(O81:V81) -> 0
B82: =B81+1 -> 52 | C82: TOTAL ITBIS DEDUCIBLE NO SUJETO A PROPORCIONALIDAD (49+50+51) | O82: =SUM(O79:O81) -> 0 | P82: =SUM(P79:S81) -> 0 | T82: =SUM(T79:V81) -> 0 | W82: =SUM(O82:V82) -> 0
B83: C) | C83: ITBIS SUJETO A PROPORCIONALIDAD (Art. 349 de Código Tributario)
B84: =B82+1 -> 53 | C84: ITBIS SUJETO A PROPORCIONALIDAD | W84: =SUM(O84:V84) -> 0
B85: =B84+1 -> 54 | C85: COEFICIENTE DE PROPORCIONALIDAD ((((Casillas 2 + 5 + 10 del IT1) / Casilla 1 del IT1)) * 100) Si aplica. | W85: =IF('IT-1'!V17+'IT-1'!V18+'IT-1'!V22+'IT-1'!V20+'IT-1'!V21=0,0,IFERROR(('IT-1'!V16+'IT-1'!V19+'IT-1'!V25)/'IT-1'!V14,0)) -> 0
B86: =B85+1 -> 55 | C86: ITBIS ADMITIDO POR APLICACIÓN DE PROPORCIONALIDAD (Casillas 53 * 54) | O86: =+O84*W85 -> 0 | P86: =+P84*W85 -> 0 | T86: =+T84*W85 -> 0 | W86: =SUM(O86:V86) -> 0
B87: =+B86+1 -> 56 | C87: TOTAL ITBIS DEDUCIBLE (52+55) | O87: =O82+O86 -> 0 | P87: =P82+P86 -> 0 | T87: =T82+T86 -> 0 | W87: =SUM(O87:V87) -> 0
B88: Nota: * Proviene del Formato de Envío de Datos 606.

Sheet IT-1
E2: DIRECCIÓN GENERAL DE IMPUESTOS INTERNOS
E3: DECLARACIÓN JURADA Y/O PAGO DEL IMPUESTO SOBRE LAS TRANSFERENCIAS DE BIENES INDUSTRIALIZADOS Y SERVICIOS (ITBIS)
B5: I. | C5: DATOS GENERALES | Z5: =IF(V14=0,1,2) -> 1
C6: RNC/CÉDULA | I6: RAZÓN SOCIAL/NOMBRE | P6: NOMBRE COMERCIAL
D9: CORREO ELECTRÓNICO | M9: TELÉFONO | P9: PERÍODO (MES/AÑO) | S9: FECHA LÍMITE DE PAGO | V9: TIPO DE DECLARACIÓN
B13: II. | C13: INGRESOS POR OPERACIONES | V13: MONTO
B14: 1 | C14: TOTAL DE OPERACIONES DEL PERIODO (Proviene de la casilla 11 del Anexo A) | U14: + | V14: ='Anexo A'!W25 -> 0
B15: II.A | C15: NO GRAVADAS
B16: =+B14+1 -> 2 | C16: INGRESOS POR EXPORTACIONES DE BIENES SEGÚN Art. 342 CT | U16: +
B17: =+B16+1 -> 3 | C17: INGRESOS POR EXPORTACIONES DE SERVICIOS SEGÚN Art. 344 CT y Art. 14 Literal j), Reglamento 293-11 | U17: +
B18: =+B17+1 -> 4 | C18: INGRESOS POR VENTAS LOCALES DE BIENES O SERVICIOS EXENTOS Art. 343 y Art. 344 CT | U18: +
B19: =+B18+1 -> 5 | C19: INGRESOS POR VENTAS DE BIENES O SERVICIOS EXENTOS POR DESTINO | U19: +
B20: =+B19+1 -> 6 | C20: NO SUJETAS A ITBIS POR SERVICIOS DE CONSTRUCCIÓN (Proviene de la casilla 38 del Anexo A) | U20: + | V20: ='Anexo A'!W60 -> 0
B21: =+B20+1 -> 7 | C21: NO SUJETAS A ITBIS POR COMISIONES (Proviene de la casilla 42 del Anexo A) | U21: + | V21: ='Anexo A'!W66 -> 0
B22: =+B21+1 -> 8 | C22: INGRESOS POR VENTAS LOCALES DE BIENES EXENTOS SEGÚN Párrafos III y IV, Art. 343 CT | U22: +
B23: =+B22+1 -> 9 | C23: TOTAL INGRESOS POR OPERACIONES NO GRAVADAS (Sumar casillas 2+3+4+5+6+7+8) | U23: = | V23: =ABS(+V16+V17+V18+V19+V20+V21+V22) -> 0
B24: II.B | C24: GRAVADAS
B25: =+B23+1 -> 10 | C25: TOTAL INGRESOS POR OPERACIONES GRAVADAS (Restar casillas 1-9) | U25: = | V25: =ABS(IF((V14-V23)>0,ABS((V14-V23)),0)) -> 0
B26: =+B25+1 -> 11 | C26: OPERACIONES GRAVADAS AL 18% | U26: =
B27: =+B26+1 -> 12 | C27: OPERACIONES GRAVADAS AL 16% | U27: =
B28: =+B27+1 -> 13 | C28: OPERACIONES GRAVADAS AL 9% (Ley No. 690-16) | U28: =
B29: =+B28+1 -> 14 | C29: OPERACIONES GRAVADAS AL 8% (Ley No. 690-16) | U29: =
B30: =+B29+1 -> 15 | C30: OPERACIONES GRAVADAS POR VENTAS DE ACTIVOS DEPRECIABLES (Categoría 2 y 3) | U30: =
B31: =IF((V26+V27+V28+V29+V30)<>V25,"La sumatoria de las casillas 11+12+13+14+15 debe ser igual al valor de la casilla 10.","")
B32: III. | C32: LIQUIDACIÓN | V32: MONTO
B33: =B30+1 -> 16 | C33: ITBIS COBRADO (18% de la casilla 11) | U33: + | V33: =ABS(+V26*18%) -> 0
B34: =+B33+1 -> 17 | C34: ITBIS COBRADO (16% de la casilla 12) | U34: + | V34: =ABS(+V27*16%) -> 0
B35: =+B34+1 -> 18 | C35: ITBIS COBRADO (9% de la casilla 13) (Ley No. 690-16) | U35: + | V35: =ABS(V28*9%) -> 0
B36: =+B35+1 -> 19 | C36: ITBIS COBRADO (8% de la casilla 14) (Ley No. 690-16) | U36: + | V36: =ABS(V29*8%) -> 0
B37: =+B36+1 -> 20 | C37: ITBIS COBRADO POR VENTAS DE ACTIVOS DEPRECIABLES (Categoría 2 y 3) (18% de la casilla 15) | U37: + | V37: =ABS(+V30*18%) -> 0
B38: =+B37+1 -> 21 | C38: TOTAL ITBIS COBRADO (Sumar casillas 16+17+18+19+20) | U38: = | V38: =ABS(V33+V34+V35+V36+V37) -> 0
B39: =+B38+1 -> 22 | C39: ITBIS PAGADO EN COMPRAS LOCALES (Proviene de la casilla 56 del Anexo A) | U39: + | V39: =+'Anexo A'!O87 -> 0
B40: =+B39+1 -> 23 | C40: ITBIS PAGADO POR SERVICIOS DEDUCIBLES (Proviene de la casilla 56 del Anexo A) | U40: + | V40: =+'Anexo A'!P87 -> 0
B41: =+B40+1 -> 24 | C41: ITBIS PAGADO EN IMPORTACIONES (Proviene de la casilla 56 del Anexo A) | U41: + | V41: =+'Anexo A'!T87 -> 0
B42: =+B41+1 -> 25 | C42: TOTAL ITBIS DEDUCIBLE (Sumar casillas 22+23+24) | U42: = | V42: =ABS(V39+V40+V41) -> 0
B43: =+B42+1 -> 26 | C43: IMPUESTO A PAGAR (Si el valor de las casillas 21-25 es Positivo) | U43: = | V43: =ABS(IF((V38-V42)>0,((V38-V42)),0)) -> 0
B44: =+B43+1 -> 27 | C44: SALDO A FAVOR (Si el valor de las casillas 21-25 es Negativo) | U44: = | V44: =ABS(IF((V38-V42)<0,(V38-V42),0)) -> 0
B45: =+B44+1 -> 28 | C45: SALDOS COMPENSABLES AUTORIZADOS (Otros Impuestos) Y/O REEMBOLSOS | U45: ±
B46: =+B45+1 -> 29 | C46: SALDO A FAVOR ANTERIOR | U46: -
B47: =+B46+1 -> 30 | C47: TOTAL PAGOS COMPUTABLES POR RETENCIONES (Proviene de la casilla 33 del Anexo A) | U47: - | V47: ='Anexo A'!W53 -> 0
B48: =+B47+1 -> 31 | C48: OTROS PAGOS COMPUTABLES A CUENTA | U48: -
B49: =+B48+1 -> 32 | C49: COMPENSACIONES Y/O REEMBOLSOS AUTORIZADOS | U49: +
B50: =+B49+1 -> 33 | C50: DIFERENCIA A PAGAR (Si el valor de las casillas 26-28-29-30-31-32 es Positivo) | U50: = | V50: =ABS(IF((V43-V45-V46-V47-V48+V49)>0,((V43-V45-V46-V47-V48+V49)),0)) -> 0
B51: =+B50+1 -> 34 | C51: NUEVO SALDO A FAVOR (Si el valor de las casillas (26-28-29-30-31-32 es Negativo) ó (27+28+29+30+31+32)) | U51: = | V51: =ABS(IF((V44+V45+V46+V47+V48-V49)>=V43,((V44+V45+V46+V47+V48-V49-V43)),0)) -> 0
B53: IV. | C53: PENALIDADES | T53: % | V53: MONTO
B54: =+B51+1 -> 35 | C54: RECARGOS | U54: + | V54: =ABS(+V50*T54) -> 0
B55: =+B54+1 -> 36 | C55: INTERÉS INDEMNIZATORIO | U55: + | V55: =ABS(+V50*T55) -> 0
B56: =+B55+1 -> 37 | C56: SANCIONES | U56: +
B58: V. | C58: MONTO A PAGAR | V58: MONTO
B59: =+B56+1 -> 38 | C59: TOTAL A PAGAR (Sumar casillas 33+35+36+37) | U59: = | V59: =ABS(V50+V54+V55+V56) -> 0
B61: A. | C61: ITBIS RETENIDO / ITBIS PERCIBIDO | V61: MONTO
B62: =B59+1 -> 39 | C62: SERVICIOS SUJETOS A RETENCIÓN PERSONAS FÍSICAS | U62: +
B63: =+B62+1 -> 40 | C63: SERVICIOS SUJETOS A RETENCIÓN ENTIDADES NO LUCRATIVAS (Norma No. 01-11) | U63: +
B64: =+B63+1 -> 41 | C64: TOTAL SERVICIOS SUJETOS A RETENCIÓN A PERSONAS FÍSICAS Y ENTIDADES NO LUCRATIVAS | U64: = | V64: =V62+V63 -> 0
B65: =+B64+1 -> 42 | C65: SERVICIOS SUJETOS A RETENCIÓN SOCIEDADES (Norma No. 07-09) | U65: =
B66: =+B65+1 -> 43 | C66: SERVICIOS SUJETOS A RETENCIÓN SOCIEDADES (Norma No. 02-05 y 07-07) | U66: =
B67: =+B66+1 -> 44 | C67: BIENES O SERVICIOS SUJETOS A RETENCIÓN A CONTRIBUYENTES ACOGIDOS AL RST (Operaciones Gravadas al 18%) | U67: +
B68: =+B67+1 -> 45 | C68: BIENES O SERVICIOS SUJETOS A RETENCIÓN A CONTRIBUYENTES ACOGIDOS AL RST (Operaciones Gravadas al 16%) | U68: +
B69: =+B68+1 -> 46 | C69: TOTAL BIENES O SERVICIOS SUJETOS A RETENCIÓN A CONTRIBUYENTES ACOGIDOS AL RST (Sumar casillas 44+45) | U69: = | V69: =ABS(V67+V68) -> 0
B70: =+B69+1 -> 47 | C70: BIENES SUJETOS A RETENCIÓN DE COMPROBANTE DE COMPRAS (Operaciones Gravadas al 18%) (Norma No. 08-10 y 05-19) | U70: +
B71: =+B70+1 -> 48 | C71: BIENES SUJETOS A RETENCIÓN DE COMPROBANTE DE COMPRAS (Operaciones Gravadas al 16%) (Norma No. 08-10 y 05-19) | U71: +
B72: =+B71+1 -> 49 | C72: TOTAL BIENES SUJETOS A RETENCIÓN COMPROBANTES DE COMPRAS (Sumar casillas 47+48) | U72: = | V72: =ABS(V70+V71) -> 0
B73: =+B72+1 -> 50 | C73: ITBIS POR SERVICIOS SUJETOS A RETENCIÓN PERSONAS FÍSICAS Y ENTIDADES NO LUCRATIVAS (18% de la casilla 41) | U73: + | V73: =ABS(V64*18%) -> 0
B74: =+B73+1 -> 51 | C74: ITBIS POR SERVICIOS SUJETOS A RETENCIÓN SOCIEDADES (18% de la casilla 42) (Norma No. 07-09) | U74: + | V74: =ABS(V65*18%) -> 0
B75: =+B74+1 -> 52 | C75: ITBIS POR SERVICIOS SUJETOS A RETENCIÓN SOCIEDADES (18% de la casilla 43 por 0.30) (Norma No. 02-05 y 07-07) | U75: + | V75: =ABS(V66*18%)*0.3 -> 0
B76: =+B75+1 -> 53 | C76: ITBIS RETENIDO A CONTRIBUYENTES ACOGIDOS AL RST (18% de la casilla 44) | U76: + | V76: =ABS(V67*18%) -> 0
B77: =+B76+1 -> 54 | C77: ITBIS RETENIDO A CONTRIBUYENTES ACOGIDOS AL RST (16% de la casilla 45) | U77: + | V77: =ABS(V68*16%) -> 0
B78: =+B77+1 -> 55 | C78: TOTAL ITBIS RETENIDO A CONTRIBUYENTES ACOGIDOS AL RST (Sumar casillas 53+54) | U78: = | V78: =ABS(V76+V77) -> 0
B79: =+B78+1 -> 56 | C79: ITBIS POR BIENES SUJETOS A RETENCIÓN DE COMPROBANTE DE COMPRAS (18% de la casilla 47) (Norma No. 08-10 y 05-19) | U79: + | V79: =V70*18% -> 0
B80: =+B79+1 -> 57 | C80: ITBIS POR BIENES SUJETOS A RETENCIÓN DE COMPROBANTE DE COMPRAS (16% de la casilla 48) (Norma No. 08-10 y 05-19) | U80: + | V80: =V71*16% -> 0
B81: =+B80+1 -> 58 | C81: TOTAL POR BIENES SUJETOS A RETENCIÓN COMPROBANTE DE COMPRAS (Sumar casillas 56+57) | U81: = | V81: =ABS(V79+V80) -> 0
B82: =+B81+1 -> 59 | C82: TOTAL ITBIS PERCIBIDO EN VENTA | U82: =
B83: =+B82+1 -> 60 | C83: IMPUESTO A PAGAR (Sumar casillas 50+51+52+55+58+59) | U83: = | V83: =ABS(V73+V74+V75+V78+V81+V82) -> 0
B84: =+B83+1 -> 61 | C84: PAGOS COMPUTABLES A CUENTA | U84: -
B85: =+B84+1 -> 62 | C85: DIFERENCIA A PAGAR (Si el valor de las casillas 60-61 es Positivo) | U85: = | V85: =IF((V83-V84)>0,ABS((V83-V84)),0) -> 0
B86: =+B85+1 -> 63 | C86: NUEVO SALDO A FAVOR (Si el valor de las casillas 60-61 es Negativo) | U86: = | V86: =IF((V83-V84)<0,ABS((V83-V84)),0) -> 0
B88: B. | C88: PENALIDADES | T88: % | V88: MONTO
B89: =+B86+1 -> 64 | C89: RECARGOS | U89: + | V89: =ABS(V85*T89) -> 0
B90: =+B89+1 -> 65 | C90: INTERÉS INDEMNIZATORIO | U90: + | V90: =ABS(V85*T90) -> 0
B91: =+B90+1 -> 66 | C91: SANCIONES | U91: +
B93: C. | C93: MONTO A PAGAR | V93: MONTO
B94: =+B91+1 -> 67 | C94: TOTAL A PAGAR (Sumar casillas 62+64+65+66) | U94: = | V94: =ABS(V85+V89+V90+V91) -> 0
B95: =IF(OR((V79)<((V70*18%)*75%),(V80)<((V71*16%)*75%)),"La Retención de Comprobantes de Compras (Casillas 57 y 58) no puede ser menor al 75% del 18% o 16% de Bienes sujetos a Retención de Comprobantes de Compras (Casilla 47 y 48).","")
B96: =+B94+1 -> 68 | C96: TOTAL GENERAL (Sumar casillas 38+67) | U96: = | V96: =V59+V94 -> 0
C99: JURAMENTO
B101: Yo, | L101: en mi calidad de | O101: por la presente afirmo bajo juramento que los datos consignados en la presente declaración son correctos y completos
B102: y que no he omitido ni falseado dato alguno que la misma deba contener, siendo en consecuencia todo su contenido la fiel expresión de la verdad.
C104: Fecha | G104: Firma
C106: PARA USO DE LA DGII
C108: Fecha de Pago | H108: No. Recibo de Pago | P108: Fecha Límite de Pago
R111: Firma del Cajero
